setup.py
jkdaae/__init__.py
jkdaae/func.py
jkdaae/osspath.py
jkdaae/spark.py
jkdaae/table.py
jkdaae/udff.py
jkdaae.egg-info/PKG-INFO
jkdaae.egg-info/SOURCES.txt
jkdaae.egg-info/dependency_links.txt
jkdaae.egg-info/requires.txt
jkdaae.egg-info/top_level.txt