Metadata-Version: 1.2
Name: jkdaae
Version: 1.0
Summary: jike project
Home-page: https://github.com/users/Melting889/projects
Maintainer: jike data analysis group
Maintainer-email: liubingfeng@clickwifi.net
License: MIT License
Platform: UNKNOWN
